zabel/elements/clients/__init__.py
zabel/elements/clients/artifactory.py
zabel/elements/clients/atlassian.py
zabel/elements/clients/confluence.py
zabel/elements/clients/confluencecloud.py
zabel/elements/clients/github.py
zabel/elements/clients/githubcloud.py
zabel/elements/clients/gitlab.py
zabel/elements/clients/jenkins.py
zabel/elements/clients/jira.py
zabel/elements/clients/jiracloud.py
zabel/elements/clients/kubehelpers.py
zabel/elements/clients/kubernetes.py
zabel/elements/clients/okta.py
zabel/elements/clients/sonarqube.py
zabel/elements/clients/sonatypenexus.py
zabel/elements/clients/squashtm.py
zabel/elements/clients/base/__init__.py
zabel/elements/clients/base/artifactory.py
zabel/elements/clients/base/atlassian.py
zabel/elements/clients/base/confluence.py
zabel/elements/clients/base/confluencecloud.py
zabel/elements/clients/base/github.py
zabel/elements/clients/base/githubcloud.py
zabel/elements/clients/base/gitlab.py
zabel/elements/clients/base/jenkins.py
zabel/elements/clients/base/jira.py
zabel/elements/clients/base/jiracloud.py
zabel/elements/clients/base/kubernetes.py
zabel/elements/clients/base/okta.py
zabel/elements/clients/base/sonarqube.py
zabel/elements/clients/base/sonatypenexus.py
zabel/elements/clients/base/squashtm.py
zabel/elements/images/__init__.py
zabel/elements/images/managedserviceapp.py
zabel/elements/images/utilityapp.py
zabel_elements-1.42.0.dist-info/LICENSE.txt
zabel_elements-1.42.0.dist-info/METADATA
zabel_elements-1.42.0.dist-info/WHEEL
zabel_elements-1.42.0.dist-info/top_level.txt
zabel_elements-1.42.0.dist-info/RECORD
