Metadata-Version: 2.2
Name: zabel-elements
Version: 1.42.0
Summary: The Zabel default clients and images
Home-page: https://github.com/engie-group/zabel
Author: Martin Lafaix
Author-email: martin.lafaix@external.engie.com
License: Eclipse Public License 2.0
Classifier: Development Status :: 5 - Production/Stable
Classifier: Programming Language :: Python :: 3
Classifier: License :: OSI Approved :: Eclipse Public License 2.0 (EPL-2.0)
Classifier: Operating System :: OS Independent
Classifier: Topic :: Software Development :: Libraries
Requires-Python: >= 3.12.0
License-File: LICENSE.txt
Requires-Dist: zabel-commons>=1.8
Provides-Extra: gitlab
Requires-Dist: python-gitlab>=6.1; extra == "gitlab"
Provides-Extra: jira
Requires-Dist: Jira>=3.0; extra == "jira"
Provides-Extra: kubernetes
Requires-Dist: kubernetes>=33.1.0; extra == "kubernetes"
Provides-Extra: okta
Requires-Dist: okta<=2.9.10,>=2.9; extra == "okta"
Provides-Extra: pynacl
Requires-Dist: pynacl>=1.5.0; extra == "pynacl"
Provides-Extra: all
Requires-Dist: Jira>=3.0; extra == "all"
Requires-Dist: kubernetes>=33.1.0; extra == "all"
Requires-Dist: okta<=2.9.10,>=2.9; extra == "all"
Requires-Dist: pynacl>=1.5.0; extra == "all"
Requires-Dist: python-gitlab>=6.1; extra == "all"
Dynamic: author
Dynamic: author-email
Dynamic: classifier
Dynamic: description
Dynamic: description-content-type
Dynamic: home-page
Dynamic: license
Dynamic: provides-extra
Dynamic: requires-dist
Dynamic: requires-python
Dynamic: summary
